odoo10_addon_stock_inventory_exclude_sublocation-10.0.1.0.0-py2.7-nspkg.pth
odoo/addons/stock_inventory_exclude_sublocation/README.rst
odoo/addons/stock_inventory_exclude_sublocation/__init__.py
odoo/addons/stock_inventory_exclude_sublocation/__manifest__.py
odoo/addons/stock_inventory_exclude_sublocation/i18n/de.po
odoo/addons/stock_inventory_exclude_sublocation/i18n/es.po
odoo/addons/stock_inventory_exclude_sublocation/i18n/es_ES.po
odoo/addons/stock_inventory_exclude_sublocation/i18n/fr.po
odoo/addons/stock_inventory_exclude_sublocation/i18n/it.po
odoo/addons/stock_inventory_exclude_sublocation/i18n/pt_BR.po
odoo/addons/stock_inventory_exclude_sublocation/i18n/sl.po
odoo/addons/stock_inventory_exclude_sublocation/models/__init__.py
odoo/addons/stock_inventory_exclude_sublocation/models/stock_inventory.py
odoo/addons/stock_inventory_exclude_sublocation/static/description/icon.png
odoo/addons/stock_inventory_exclude_sublocation/tests/__init__.py
odoo/addons/stock_inventory_exclude_sublocation/tests/test_exclude_sublocation.py
odoo/addons/stock_inventory_exclude_sublocation/views/stock_inventory_view.xml
odoo10_addon_stock_inventory_exclude_sublocation-10.0.1.0.0.dist-info/DESCRIPTION.rst
odoo10_addon_stock_inventory_exclude_sublocation-10.0.1.0.0.dist-info/METADATA
odoo10_addon_stock_inventory_exclude_sublocation-10.0.1.0.0.dist-info/RECORD
odoo10_addon_stock_inventory_exclude_sublocation-10.0.1.0.0.dist-info/WHEEL
odoo10_addon_stock_inventory_exclude_sublocation-10.0.1.0.0.dist-info/metadata.json
odoo10_addon_stock_inventory_exclude_sublocation-10.0.1.0.0.dist-info/namespace_packages.txt
odoo10_addon_stock_inventory_exclude_sublocation-10.0.1.0.0.dist-info/top_level.txt
