Metadata-Version: 2.0
Name: odoo10-addon-stock-inventory-exclude-sublocation
Version: 10.0.1.0.0
Summary: Allow to perform inventories of a location without including its child locations.
Home-page: https://github.com/OCA/stock-logistics-warehouse
Author: Eficent,Odoo Community Association (OCA)
Author-email: support@odoo-community.org
License: AGPL-3
Platform: UNKNOWN
Classifier: Programming Language :: Python :: 2.7
Classifier: Framework :: Odoo
Classifier: License :: OSI Approved :: GNU Affero General Public License v3
Requires-Dist: odoo (<10.1dev,>=10.0)
Requires-Dist: odoo10-addon-stock-inventory-chatter
